spiderspt/__init__.py
spiderspt/execjs_.py
spiderspt/logger_.py
spiderspt/ocr_captcha_.py
spiderspt-0.2.3.dist-info/METADATA
spiderspt-0.2.3.dist-info/WHEEL
spiderspt-0.2.3.dist-info/RECORD
