Metadata-Version: 2.4
Name: spiderspt
Version: 0.2.3
Summary: 一个爬虫中可能使用到的各种工具集合
Author-email: distant <2560389931@qq.com>
Requires-Python: >=3.10
Requires-Dist: exejs>=0.0.6
Requires-Dist: loguru>=0.7.3
Requires-Dist: psutil>=7.2.1
Requires-Dist: requests>=2.32.5
